vonage_video/__init__.py
vonage_video/_version.py
vonage_video/errors.py
vonage_video/video.py
vonage_video/models/__init__.py
vonage_video/models/archive.py
vonage_video/models/audio_connector.py
vonage_video/models/broadcast.py
vonage_video/models/captions.py
vonage_video/models/common.py
vonage_video/models/enums.py
vonage_video/models/experience_composer.py
vonage_video/models/session.py
vonage_video/models/signal.py
vonage_video/models/sip.py
vonage_video/models/stream.py
vonage_video/models/token.py
vonage_video-1.5.0.dist-info/METADATA
vonage_video-1.5.0.dist-info/WHEEL
vonage_video-1.5.0.dist-info/top_level.txt
vonage_video-1.5.0.dist-info/RECORD
